minumtium_postgres/__init__.py
minumtium_postgres/migrations/__init__.py
minumtium_postgres/migrations/versions/__init__.py
minumtium_postgres/migrations/versions/version_0.py
minumtium_postgres/migrations/versions/version_1.py
minumtium_postgres-1.2.3.dist-info/LICENSE
minumtium_postgres-1.2.3.dist-info/METADATA
minumtium_postgres-1.2.3.dist-info/WHEEL
minumtium_postgres-1.2.3.dist-info/top_level.txt
minumtium_postgres-1.2.3.dist-info/RECORD
