Metadata-Version: 2.1
Name: minumtium-postgres
Version: 1.2.3
Summary: A postgres database adapter for the minumtium library.
Home-page: https://github.com/pypa/sampleproject
Author: Danilo Guimaraes (danodic)
Author-email: danilo@danodic.dev
Project-URL: Bug Tracker, https://github.com/pypa/sampleproject/issues
Classifier: Programming Language :: Python :: 3
Classifier: License :: OSI Approved :: MIT License
Classifier: Operating System :: OS Independent
Requires-Python: >=3.6
License-File: LICENSE
Requires-Dist: sqlalchemy
Requires-Dist: pg8000
Requires-Dist: minumtium
Requires-Dist: pydantic
